cron_converter/__init__.py
cron_converter/cron.py
cron_converter/sub_modules/part.py
cron_converter/sub_modules/seeker.py
cron_converter/sub_modules/units.py
cron_converter/sub_modules/utils.py
cron_converter-1.2.0.dist-info/LICENSE
cron_converter-1.2.0.dist-info/METADATA
cron_converter-1.2.0.dist-info/WHEEL
cron_converter-1.2.0.dist-info/top_level.txt
cron_converter-1.2.0.dist-info/RECORD
