Metadata-Version: 2.1
Name: cron-converter
Version: 1.2.0
Summary: Cron string parser and scheduler for Python
Author-email: Andrea Salvatori <16443598+Sonic0@users.noreply.github.com>
Project-URL: Homepage, https://github.com/Sonic0/cron-converter
Project-URL: Issues, https://github.com/Sonic0/cron-converter/issues
Classifier: Development Status :: 5 - Production/Stable
Classifier: Intended Audience :: Developers
Classifier: Intended Audience :: System Administrators
Classifier: License :: OSI Approved :: MIT License
Classifier: Programming Language :: Python :: 3
Classifier: Programming Language :: Python :: 3 :: Only
Classifier: Operating System :: OS Independent
Classifier: Topic :: Software Development :: Libraries :: Python Modules
Requires-Python: >=3.8
License-File: LICENSE
Requires-Dist: python-dateutil
Provides-Extra: mypy
Requires-Dist: mypy ; extra == 'mypy'
Requires-Dist: types-python-dateutil ; extra == 'mypy'
Provides-Extra: test
Requires-Dist: python-dateutil ; extra == 'test'
